[
  {
    "direction": "Flat", 
    "trend": 4, 
    "dateString": "2016-02-21T17:49:33.000Z", 
    "sgv": 101, 
    "device": "share2", 
    "date": 1456076973000, 
    "_id": "56c9f8c737663704c8478314", 
    "type": "sgv"
  }, 
  {
    "direction": "Flat", 
    "trend": 4, 
    "dateString": "2016-02-21T17:44:28.000Z", 
    "sgv": 97, 
    "device": "share2", 
    "date": 1456076668000, 
    "_id": "56c9f79b37663704c8478307", 
    "type": "sgv"
  }, 
  {
    "direction": "Flat", 
    "trend": 4, 
    "dateString": "2016-02-21T17:39:38.000Z", 
    "sgv": 94, 
    "device": "share2", 
    "date": 1456076378000, 
    "_id": "56c9f66f37663704c84782fc", 
    "type": "sgv"
  }, 
  {
    "direction": "Flat", 
    "trend": 4, 
    "dateString": "2016-02-21T17:34:35.000Z", 
    "sgv": 92, 
    "device": "share2", 
    "date": 1456076075000, 
    "_id": "56c9f54337663704c84782f1", 
    "type": "sgv"
  }, 
  {
    "direction": "Flat", 
    "trend": 4, 
    "dateString": "2016-02-21T17:29:47.000Z", 
    "sgv": 94, 
    "device": "share2", 
    "date": 1456075787000, 
    "_id": "56c9f41737663704c84782e8", 
    "type": "sgv"
  }, 
  {
    "direction": "Flat", 
    "trend": 4, 
    "dateString": "2016-02-21T17:24:28.000Z", 
    "sgv": 94, 
    "device": "share2", 
    "date": 1456075468000, 
    "_id": "56c9f2eb37663704c84782db", 
    "type": "sgv"
  }, 
  {
    "direction": "Flat", 
    "trend": 4, 
    "dateString": "2016-02-21T17:19:27.000Z", 
    "sgv": 92, 
    "device": "share2", 
    "date": 1456075167000, 
    "_id": "56c9f1c037663704c84782d0", 
    "type": "sgv"
  }, 
  {
    "direction": "Flat", 
    "trend": 4, 
    "dateString": "2016-02-21T17:14:28.000Z", 
    "sgv": 90, 
    "device": "share2", 
    "date": 1456074868000, 
    "_id": "56c9f09337663704c84782c5", 
    "type": "sgv"
  }, 
  {
    "direction": "Flat", 
    "trend": 4, 
    "dateString": "2016-02-21T17:09:30.000Z", 
    "sgv": 92, 
    "device": "share2", 
    "date": 1456074570000, 
    "_id": "56c9ef6737663704c84782b9", 
    "type": "sgv"
  }, 
  {
    "direction": "Flat", 
    "trend": 4, 
    "dateString": "2016-02-21T17:04:28.000Z", 
    "sgv": 92, 
    "device": "share2", 
    "date": 1456074268000, 
    "_id": "56c9ee3b37663704c84782ac", 
    "type": "sgv"
  }
]