[
  {
    "direction": "Flat", 
    "trend": 4, 
    "dateString": "2016-02-18T22:04:34.000Z", 
    "sgv": 93, 
    "device": "share2", 
    "date": 1455833074000, 
    "_id": "56c63fff37663704c8475b72", 
    "type": "sgv"
  }, 
  {
    "direction": "Flat", 
    "trend": 4, 
    "dateString": "2016-02-18T21:59:36.000Z", 
    "sgv": 95, 
    "device": "share2", 
    "date": 1455832776000, 
    "_id": "56c63ed337663704c8475b68", 
    "type": "sgv"
  }, 
  {
    "direction": "Flat", 
    "trend": 4, 
    "dateString": "2016-02-18T21:54:35.000Z", 
    "sgv": 98, 
    "device": "share2", 
    "date": 1455832475000, 
    "_id": "56c63da737663704c8475b5b", 
    "type": "sgv"
  }, 
  {
    "direction": "Flat", 
    "trend": 4, 
    "dateString": "2016-02-18T21:49:34.000Z", 
    "sgv": 99, 
    "device": "share2", 
    "date": 1455832174000, 
    "_id": "56c63c7b37663704c8475b51", 
    "type": "sgv"
  }, 
  {
    "direction": "Flat", 
    "trend": 4, 
    "dateString": "2016-02-18T21:44:34.000Z", 
    "sgv": 102, 
    "device": "share2", 
    "date": 1455831874000, 
    "_id": "56c63b4f37663704c8475b44", 
    "type": "sgv"
  }, 
  {
    "direction": "Flat", 
    "trend": 4, 
    "dateString": "2016-02-18T21:39:34.000Z", 
    "sgv": 104, 
    "device": "share2", 
    "date": 1455831574000, 
    "_id": "56c63a2337663704c8475b3a", 
    "type": "sgv"
  }, 
  {
    "direction": "Flat", 
    "trend": 4, 
    "dateString": "2016-02-18T21:34:34.000Z", 
    "sgv": 106, 
    "device": "share2", 
    "date": 1455831274000, 
    "_id": "56c638f737663704c8475b29", 
    "type": "sgv"
  }, 
  {
    "direction": "Flat", 
    "trend": 4, 
    "dateString": "2016-02-18T21:29:37.000Z", 
    "sgv": 108, 
    "device": "share2", 
    "date": 1455830977000, 
    "_id": "56c637cc37663704c8475b1e", 
    "type": "sgv"
  }, 
  {
    "direction": "Flat", 
    "trend": 4, 
    "dateString": "2016-02-18T21:24:35.000Z", 
    "sgv": 111, 
    "device": "share2", 
    "date": 1455830675000, 
    "_id": "56c6369f37663704c8475b0d", 
    "type": "sgv"
  }, 
  {
    "direction": "Flat", 
    "trend": 4, 
    "dateString": "2016-02-18T21:19:35.000Z", 
    "sgv": 113, 
    "device": "share2", 
    "date": 1455830375000, 
    "_id": "56c6357437663704c8475b01", 
    "type": "sgv"
  }
]