[
  {
    "_type": "TempBasalDuration", 
    "duration (min)": 30, 
    "_description": "TempBasalDuration 2016-02-18T19:43:59 head[2], body[0] op[0x16]", 
    "timestamp": "2016-02-18T19:43:59", 
    "_body": "", 
    "_head": "1601", 
    "_date": "3bab135210"
  }, 
  {
    "_type": "TempBasal", 
    "temp": "absolute", 
    "_description": "TempBasal 2016-02-18T19:43:59 head[2], body[1] op[0x33]", 
    "timestamp": "2016-02-18T19:43:59", 
    "_body": "00", 
    "_head": "3300", 
    "rate": 0.0, 
    "_date": "3bab135210"
  }, 
  {
    "_type": "TempBasalDuration", 
    "duration (min)": 30, 
    "_description": "TempBasalDuration 2016-02-18T19:43:56 head[2], body[0] op[0x16]", 
    "timestamp": "2016-02-18T19:43:56", 
    "_body": "", 
    "_head": "1601", 
    "_date": "38ab135210"
  }, 
  {
    "_type": "TempBasal", 
    "temp": "absolute", 
    "_description": "TempBasal 2016-02-18T19:43:56 head[2], body[1] op[0x33]", 
    "timestamp": "2016-02-18T19:43:56", 
    "_body": "00", 
    "_head": "3300", 
    "rate": 0.0, 
    "_date": "38ab135210"
  }, 
  {
    "_type": "TempBasalDuration", 
    "duration (min)": 30, 
    "_description": "TempBasalDuration 2016-02-18T19:43:55 head[2], body[0] op[0x16]", 
    "timestamp": "2016-02-18T19:43:55", 
    "_body": "", 
    "_head": "1601", 
    "_date": "37ab135210"
  }, 
  {
    "_type": "TempBasal", 
    "temp": "absolute", 
    "_description": "TempBasal 2016-02-18T19:43:55 head[2], body[1] op[0x33]", 
    "timestamp": "2016-02-18T19:43:55", 
    "_body": "00", 
    "_head": "3300", 
    "rate": 0.0, 
    "_date": "37ab135210"
  }, 
  {
    "_type": "TempBasalDuration", 
    "duration (min)": 30, 
    "_description": "TempBasalDuration 2016-02-18T19:38:56 head[2], body[0] op[0x16]", 
    "timestamp": "2016-02-18T19:38:56", 
    "_body": "", 
    "_head": "1601", 
    "_date": "38a6135210"
  }, 
  {
    "_type": "TempBasal", 
    "temp": "absolute", 
    "_description": "TempBasal 2016-02-18T19:38:56 head[2], body[1] op[0x33]", 
    "timestamp": "2016-02-18T19:38:56", 
    "_body": "00", 
    "_head": "3300", 
    "rate": 0.0, 
    "_date": "38a6135210"
  }, 
  {
    "_type": "TempBasalDuration", 
    "duration (min)": 30, 
    "_description": "TempBasalDuration 2016-02-18T19:38:53 head[2], body[0] op[0x16]", 
    "timestamp": "2016-02-18T19:38:53", 
    "_body": "", 
    "_head": "1601", 
    "_date": "35a6135210"
  }, 
  {
    "_type": "TempBasal", 
    "temp": "absolute", 
    "_description": "TempBasal 2016-02-18T19:38:53 head[2], body[1] op[0x33]", 
    "timestamp": "2016-02-18T19:38:53", 
    "_body": "00", 
    "_head": "3300", 
    "rate": 0.0, 
    "_date": "35a6135210"
  }, 
  {
    "_type": "TempBasalDuration", 
    "duration (min)": 30, 
    "_description": "TempBasalDuration 2016-02-18T19:38:52 head[2], body[0] op[0x16]", 
    "timestamp": "2016-02-18T19:38:52", 
    "_body": "", 
    "_head": "1601", 
    "_date": "34a6135210"
  }, 
  {
    "_type": "TempBasal", 
    "temp": "absolute", 
    "_description": "TempBasal 2016-02-18T19:38:52 head[2], body[1] op[0x33]", 
    "timestamp": "2016-02-18T19:38:52", 
    "_body": "00", 
    "_head": "3300", 
    "rate": 0.0, 
    "_date": "34a6135210"
  }, 
  {
    "_type": "TempBasalDuration", 
    "duration (min)": 30, 
    "_description": "TempBasalDuration 2016-02-18T19:33:01 head[2], body[0] op[0x16]", 
    "timestamp": "2016-02-18T19:33:01", 
    "_body": "", 
    "_head": "1601", 
    "_date": "01a1135210"
  }, 
  {
    "_type": "TempBasal", 
    "temp": "absolute", 
    "_description": "TempBasal 2016-02-18T19:33:01 head[2], body[1] op[0x33]", 
    "timestamp": "2016-02-18T19:33:01", 
    "_body": "00", 
    "_head": "3300", 
    "rate": 0.0, 
    "_date": "01a1135210"
  }, 
  {
    "_type": "TempBasalDuration", 
    "duration (min)": 30, 
    "_description": "TempBasalDuration 2016-02-18T19:32:58 head[2], body[0] op[0x16]", 
    "timestamp": "2016-02-18T19:32:58", 
    "_body": "", 
    "_head": "1601", 
    "_date": "3aa0135210"
  }, 
  {
    "_type": "TempBasal", 
    "temp": "absolute", 
    "_description": "TempBasal 2016-02-18T19:32:58 head[2], body[1] op[0x33]", 
    "timestamp": "2016-02-18T19:32:58", 
    "_body": "00", 
    "_head": "3300", 
    "rate": 0.0, 
    "_date": "3aa0135210"
  }, 
  {
    "_type": "TempBasalDuration", 
    "duration (min)": 30, 
    "_description": "TempBasalDuration 2016-02-18T19:32:57 head[2], body[0] op[0x16]", 
    "timestamp": "2016-02-18T19:32:57", 
    "_body": "", 
    "_head": "1601", 
    "_date": "39a0135210"
  }, 
  {
    "_type": "TempBasal", 
    "temp": "absolute", 
    "_description": "TempBasal 2016-02-18T19:32:57 head[2], body[1] op[0x33]", 
    "timestamp": "2016-02-18T19:32:57", 
    "_body": "00", 
    "_head": "3300", 
    "rate": 0.0, 
    "_date": "39a0135210"
  }, 
  {
    "_type": "TempBasalDuration", 
    "duration (min)": 30, 
    "_description": "TempBasalDuration 2016-02-18T19:27:57 head[2], body[0] op[0x16]", 
    "timestamp": "2016-02-18T19:27:57", 
    "_body": "", 
    "_head": "1601", 
    "_date": "399b135210"
  }, 
  {
    "_type": "TempBasal", 
    "temp": "absolute", 
    "_description": "TempBasal 2016-02-18T19:27:57 head[2], body[1] op[0x33]", 
    "timestamp": "2016-02-18T19:27:57", 
    "_body": "00", 
    "_head": "3300", 
    "rate": 0.0, 
    "_date": "399b135210"
  }, 
  {
    "_type": "TempBasalDuration", 
    "duration (min)": 30, 
    "_description": "TempBasalDuration 2016-02-18T19:27:54 head[2], body[0] op[0x16]", 
    "timestamp": "2016-02-18T19:27:54", 
    "_body": "", 
    "_head": "1601", 
    "_date": "369b135210"
  }, 
  {
    "_type": "TempBasal", 
    "temp": "absolute", 
    "_description": "TempBasal 2016-02-18T19:27:54 head[2], body[1] op[0x33]", 
    "timestamp": "2016-02-18T19:27:54", 
    "_body": "00", 
    "_head": "3300", 
    "rate": 0.0, 
    "_date": "369b135210"
  }, 
  {
    "_type": "TempBasalDuration", 
    "duration (min)": 30, 
    "_description": "TempBasalDuration 2016-02-18T19:27:53 head[2], body[0] op[0x16]", 
    "timestamp": "2016-02-18T19:27:53", 
    "_body": "", 
    "_head": "1601", 
    "_date": "359b135210"
  }, 
  {
    "_type": "TempBasal", 
    "temp": "absolute", 
    "_description": "TempBasal 2016-02-18T19:27:53 head[2], body[1] op[0x33]", 
    "timestamp": "2016-02-18T19:27:53", 
    "_body": "00", 
    "_head": "3300", 
    "rate": 0.0, 
    "_date": "359b135210"
  }, 
  {
    "_type": "TempBasalDuration", 
    "duration (min)": 30, 
    "_description": "TempBasalDuration 2016-02-18T19:18:56 head[2], body[0] op[0x16]", 
    "timestamp": "2016-02-18T19:18:56", 
    "_body": "", 
    "_head": "1601", 
    "_date": "3892135210"
  }, 
  {
    "_type": "TempBasal", 
    "temp": "absolute", 
    "_description": "TempBasal 2016-02-18T19:18:56 head[2], body[1] op[0x33]", 
    "timestamp": "2016-02-18T19:18:56", 
    "_body": "00", 
    "_head": "3300", 
    "rate": 0.0, 
    "_date": "3892135210"
  }, 
  {
    "_type": "TempBasalDuration", 
    "duration (min)": 30, 
    "_description": "TempBasalDuration 2016-02-18T19:18:53 head[2], body[0] op[0x16]", 
    "timestamp": "2016-02-18T19:18:53", 
    "_body": "", 
    "_head": "1601", 
    "_date": "3592135210"
  }, 
  {
    "_type": "TempBasal", 
    "temp": "absolute", 
    "_description": "TempBasal 2016-02-18T19:18:53 head[2], body[1] op[0x33]", 
    "timestamp": "2016-02-18T19:18:53", 
    "_body": "00", 
    "_head": "3300", 
    "rate": 0.0, 
    "_date": "3592135210"
  }, 
  {
    "_type": "TempBasalDuration", 
    "duration (min)": 30, 
    "_description": "TempBasalDuration 2016-02-18T19:18:52 head[2], body[0] op[0x16]", 
    "timestamp": "2016-02-18T19:18:52", 
    "_body": "", 
    "_head": "1601", 
    "_date": "3492135210"
  }, 
  {
    "_type": "TempBasal", 
    "temp": "absolute", 
    "_description": "TempBasal 2016-02-18T19:18:52 head[2], body[1] op[0x33]", 
    "timestamp": "2016-02-18T19:18:52", 
    "_body": "00", 
    "_head": "3300", 
    "rate": 0.0, 
    "_date": "3492135210"
  }, 
  {
    "_type": "TempBasalDuration", 
    "duration (min)": 30, 
    "_description": "TempBasalDuration 2016-02-18T19:13:12 head[2], body[0] op[0x16]", 
    "timestamp": "2016-02-18T19:13:12", 
    "_body": "", 
    "_head": "1601", 
    "_date": "0c8d135210"
  }, 
  {
    "_type": "TempBasal", 
    "temp": "absolute", 
    "_description": "TempBasal 2016-02-18T19:13:12 head[2], body[1] op[0x33]", 
    "timestamp": "2016-02-18T19:13:12", 
    "_body": "00", 
    "_head": "3300", 
    "rate": 0.0, 
    "_date": "0c8d135210"
  }, 
  {
    "_type": "TempBasalDuration", 
    "duration (min)": 30, 
    "_description": "TempBasalDuration 2016-02-18T19:13:10 head[2], body[0] op[0x16]", 
    "timestamp": "2016-02-18T19:13:10", 
    "_body": "", 
    "_head": "1601", 
    "_date": "0a8d135210"
  }, 
  {
    "_type": "TempBasal", 
    "temp": "absolute", 
    "_description": "TempBasal 2016-02-18T19:13:10 head[2], body[1] op[0x33]", 
    "timestamp": "2016-02-18T19:13:10", 
    "_body": "00", 
    "_head": "3300", 
    "rate": 0.0, 
    "_date": "0a8d135210"
  }, 
  {
    "_type": "TempBasalDuration", 
    "duration (min)": 30, 
    "_description": "TempBasalDuration 2016-02-18T19:13:08 head[2], body[0] op[0x16]", 
    "timestamp": "2016-02-18T19:13:08", 
    "_body": "", 
    "_head": "1601", 
    "_date": "088d135210"
  }, 
  {
    "_type": "TempBasal", 
    "temp": "absolute", 
    "_description": "TempBasal 2016-02-18T19:13:08 head[2], body[1] op[0x33]", 
    "timestamp": "2016-02-18T19:13:08", 
    "_body": "00", 
    "_head": "3300", 
    "rate": 0.0, 
    "_date": "088d135210"
  }, 
  {
    "_type": "TempBasalDuration", 
    "duration (min)": 0, 
    "_description": "TempBasalDuration 2016-02-18T18:29:01 head[2], body[0] op[0x16]", 
    "timestamp": "2016-02-18T18:29:01", 
    "_body": "", 
    "_head": "1600", 
    "_date": "019d125210"
  }, 
  {
    "_type": "TempBasal", 
    "temp": "absolute", 
    "_description": "TempBasal 2016-02-18T18:29:01 head[2], body[1] op[0x33]", 
    "timestamp": "2016-02-18T18:29:01", 
    "_body": "00", 
    "_head": "3300", 
    "rate": 0.0, 
    "_date": "019d125210"
  }, 
  {
    "_type": "TempBasalDuration", 
    "duration (min)": 0, 
    "_description": "TempBasalDuration 2016-02-18T18:28:59 head[2], body[0] op[0x16]", 
    "timestamp": "2016-02-18T18:28:59", 
    "_body": "", 
    "_head": "1600", 
    "_date": "3b9c125210"
  }, 
  {
    "_type": "TempBasal", 
    "temp": "absolute", 
    "_description": "TempBasal 2016-02-18T18:28:59 head[2], body[1] op[0x33]", 
    "timestamp": "2016-02-18T18:28:59", 
    "_body": "00", 
    "_head": "3300", 
    "rate": 0.0, 
    "_date": "3b9c125210"
  }, 
  {
    "_type": "TempBasalDuration", 
    "duration (min)": 0, 
    "_description": "TempBasalDuration 2016-02-18T18:28:57 head[2], body[0] op[0x16]", 
    "timestamp": "2016-02-18T18:28:57", 
    "_body": "", 
    "_head": "1600", 
    "_date": "399c125210"
  }, 
  {
    "_type": "TempBasal", 
    "temp": "absolute", 
    "_description": "TempBasal 2016-02-18T18:28:57 head[2], body[1] op[0x33]", 
    "timestamp": "2016-02-18T18:28:57", 
    "_body": "00", 
    "_head": "3300", 
    "rate": 0.0, 
    "_date": "399c125210"
  }, 
  {
    "_type": "TempBasalDuration", 
    "duration (min)": 30, 
    "_description": "TempBasalDuration 2016-02-18T18:20:53 head[2], body[0] op[0x16]", 
    "timestamp": "2016-02-18T18:20:53", 
    "_body": "", 
    "_head": "1601", 
    "_date": "3594125210"
  }, 
  {
    "_type": "TempBasal", 
    "temp": "absolute", 
    "_description": "TempBasal 2016-02-18T18:20:53 head[2], body[1] op[0x33]", 
    "timestamp": "2016-02-18T18:20:53", 
    "_body": "00", 
    "_head": "3300", 
    "rate": 0.0, 
    "_date": "3594125210"
  }, 
  {
    "_type": "TempBasalDuration", 
    "duration (min)": 30, 
    "_description": "TempBasalDuration 2016-02-18T18:20:50 head[2], body[0] op[0x16]", 
    "timestamp": "2016-02-18T18:20:50", 
    "_body": "", 
    "_head": "1601", 
    "_date": "3294125210"
  }, 
  {
    "_type": "TempBasal", 
    "temp": "absolute", 
    "_description": "TempBasal 2016-02-18T18:20:50 head[2], body[1] op[0x33]", 
    "timestamp": "2016-02-18T18:20:50", 
    "_body": "00", 
    "_head": "3300", 
    "rate": 0.0, 
    "_date": "3294125210"
  }, 
  {
    "_type": "TempBasalDuration", 
    "duration (min)": 30, 
    "_description": "TempBasalDuration 2016-02-18T18:20:49 head[2], body[0] op[0x16]", 
    "timestamp": "2016-02-18T18:20:49", 
    "_body": "", 
    "_head": "1601", 
    "_date": "3194125210"
  }, 
  {
    "_type": "TempBasal", 
    "temp": "absolute", 
    "_description": "TempBasal 2016-02-18T18:20:49 head[2], body[1] op[0x33]", 
    "timestamp": "2016-02-18T18:20:49", 
    "_body": "00", 
    "_head": "3300", 
    "rate": 0.0, 
    "_date": "3194125210"
  }, 
  {
    "_type": "TempBasalDuration", 
    "duration (min)": 30, 
    "_description": "TempBasalDuration 2016-02-18T18:15:57 head[2], body[0] op[0x16]", 
    "timestamp": "2016-02-18T18:15:57", 
    "_body": "", 
    "_head": "1601", 
    "_date": "398f125210"
  }, 
  {
    "_type": "TempBasal", 
    "temp": "absolute", 
    "_description": "TempBasal 2016-02-18T18:15:57 head[2], body[1] op[0x33]", 
    "timestamp": "2016-02-18T18:15:57", 
    "_body": "00", 
    "_head": "3300", 
    "rate": 0.0, 
    "_date": "398f125210"
  }, 
  {
    "_type": "TempBasalDuration", 
    "duration (min)": 30, 
    "_description": "TempBasalDuration 2016-02-18T18:15:56 head[2], body[0] op[0x16]", 
    "timestamp": "2016-02-18T18:15:56", 
    "_body": "", 
    "_head": "1601", 
    "_date": "388f125210"
  }, 
  {
    "_type": "TempBasal", 
    "temp": "absolute", 
    "_description": "TempBasal 2016-02-18T18:15:56 head[2], body[1] op[0x33]", 
    "timestamp": "2016-02-18T18:15:56", 
    "_body": "00", 
    "_head": "3300", 
    "rate": 0.0, 
    "_date": "388f125210"
  }, 
  {
    "_type": "TempBasalDuration", 
    "duration (min)": 0, 
    "_description": "TempBasalDuration 2016-02-18T17:15:21 head[2], body[0] op[0x16]", 
    "timestamp": "2016-02-18T17:15:21", 
    "_body": "", 
    "_head": "1600", 
    "_date": "158f115210"
  }, 
  {
    "_type": "TempBasal", 
    "temp": "absolute", 
    "_description": "TempBasal 2016-02-18T17:15:21 head[2], body[1] op[0x33]", 
    "timestamp": "2016-02-18T17:15:21", 
    "_body": "00", 
    "_head": "3300", 
    "rate": 0.0, 
    "_date": "158f115210"
  }, 
  {
    "_type": "TempBasalDuration", 
    "duration (min)": 0, 
    "_description": "TempBasalDuration 2016-02-18T17:15:19 head[2], body[0] op[0x16]", 
    "timestamp": "2016-02-18T17:15:19", 
    "_body": "", 
    "_head": "1600", 
    "_date": "138f115210"
  }, 
  {
    "_type": "TempBasal", 
    "temp": "absolute", 
    "_description": "TempBasal 2016-02-18T17:15:19 head[2], body[1] op[0x33]", 
    "timestamp": "2016-02-18T17:15:19", 
    "_body": "00", 
    "_head": "3300", 
    "rate": 0.0, 
    "_date": "138f115210"
  }, 
  {
    "_type": "TempBasalDuration", 
    "duration (min)": 0, 
    "_description": "TempBasalDuration 2016-02-18T17:15:18 head[2], body[0] op[0x16]", 
    "timestamp": "2016-02-18T17:15:18", 
    "_body": "", 
    "_head": "1600", 
    "_date": "128f115210"
  }, 
  {
    "_type": "TempBasal", 
    "temp": "absolute", 
    "_description": "TempBasal 2016-02-18T17:15:18 head[2], body[1] op[0x33]", 
    "timestamp": "2016-02-18T17:15:18", 
    "_body": "00", 
    "_head": "3300", 
    "rate": 0.0, 
    "_date": "128f115210"
  }, 
  {
    "_type": "TempBasalDuration", 
    "duration (min)": 30, 
    "_description": "TempBasalDuration 2016-02-18T17:06:54 head[2], body[0] op[0x16]", 
    "timestamp": "2016-02-18T17:06:54", 
    "_body": "", 
    "_head": "1601", 
    "_date": "3686115210"
  }, 
  {
    "_type": "TempBasal", 
    "temp": "absolute", 
    "_description": "TempBasal 2016-02-18T17:06:54 head[2], body[1] op[0x33]", 
    "timestamp": "2016-02-18T17:06:54", 
    "_body": "00", 
    "_head": "3300", 
    "rate": 0.0, 
    "_date": "3686115210"
  }, 
  {
    "_type": "TempBasalDuration", 
    "duration (min)": 30, 
    "_description": "TempBasalDuration 2016-02-18T17:06:51 head[2], body[0] op[0x16]", 
    "timestamp": "2016-02-18T17:06:51", 
    "_body": "", 
    "_head": "1601", 
    "_date": "3386115210"
  }, 
  {
    "_type": "TempBasal", 
    "temp": "absolute", 
    "_description": "TempBasal 2016-02-18T17:06:51 head[2], body[1] op[0x33]", 
    "timestamp": "2016-02-18T17:06:51", 
    "_body": "00", 
    "_head": "3300", 
    "rate": 0.0, 
    "_date": "3386115210"
  }, 
  {
    "_type": "TempBasalDuration", 
    "duration (min)": 30, 
    "_description": "TempBasalDuration 2016-02-18T17:06:50 head[2], body[0] op[0x16]", 
    "timestamp": "2016-02-18T17:06:50", 
    "_body": "", 
    "_head": "1601", 
    "_date": "3286115210"
  }, 
  {
    "_type": "TempBasal", 
    "temp": "absolute", 
    "_description": "TempBasal 2016-02-18T17:06:50 head[2], body[1] op[0x33]", 
    "timestamp": "2016-02-18T17:06:50", 
    "_body": "00", 
    "_head": "3300", 
    "rate": 0.0, 
    "_date": "3286115210"
  }, 
  {
    "_type": "TempBasalDuration", 
    "duration (min)": 30, 
    "_description": "TempBasalDuration 2016-02-18T17:01:55 head[2], body[0] op[0x16]", 
    "timestamp": "2016-02-18T17:01:55", 
    "_body": "", 
    "_head": "1601", 
    "_date": "3781115210"
  }, 
  {
    "_type": "TempBasal", 
    "temp": "absolute", 
    "_description": "TempBasal 2016-02-18T17:01:55 head[2], body[1] op[0x33]", 
    "timestamp": "2016-02-18T17:01:55", 
    "_body": "00", 
    "_head": "3300", 
    "rate": 0.0, 
    "_date": "3781115210"
  }, 
  {
    "_type": "TempBasalDuration", 
    "duration (min)": 30, 
    "_description": "TempBasalDuration 2016-02-18T17:01:53 head[2], body[0] op[0x16]", 
    "timestamp": "2016-02-18T17:01:53", 
    "_body": "", 
    "_head": "1601", 
    "_date": "3581115210"
  }, 
  {
    "_type": "TempBasal", 
    "temp": "absolute", 
    "_description": "TempBasal 2016-02-18T17:01:53 head[2], body[1] op[0x33]", 
    "timestamp": "2016-02-18T17:01:53", 
    "_body": "00", 
    "_head": "3300", 
    "rate": 0.0, 
    "_date": "3581115210"
  }, 
  {
    "_type": "TempBasalDuration", 
    "duration (min)": 30, 
    "_description": "TempBasalDuration 2016-02-18T17:01:51 head[2], body[0] op[0x16]", 
    "timestamp": "2016-02-18T17:01:51", 
    "_body": "", 
    "_head": "1601", 
    "_date": "3381115210"
  }, 
  {
    "_type": "TempBasal", 
    "temp": "absolute", 
    "_description": "TempBasal 2016-02-18T17:01:51 head[2], body[1] op[0x33]", 
    "timestamp": "2016-02-18T17:01:51", 
    "_body": "00", 
    "_head": "3300", 
    "rate": 0.0, 
    "_date": "3381115210"
  }, 
  {
    "_type": "TempBasalDuration", 
    "duration (min)": 30, 
    "_description": "TempBasalDuration 2016-02-18T16:56:56 head[2], body[0] op[0x16]", 
    "timestamp": "2016-02-18T16:56:56", 
    "_body": "", 
    "_head": "1601", 
    "_date": "38b8105210"
  }, 
  {
    "_type": "TempBasal", 
    "temp": "absolute", 
    "_description": "TempBasal 2016-02-18T16:56:56 head[2], body[1] op[0x33]", 
    "timestamp": "2016-02-18T16:56:56", 
    "_body": "00", 
    "_head": "3300", 
    "rate": 0.0, 
    "_date": "38b8105210"
  }, 
  {
    "_type": "TempBasalDuration", 
    "duration (min)": 30, 
    "_description": "TempBasalDuration 2016-02-18T16:56:53 head[2], body[0] op[0x16]", 
    "timestamp": "2016-02-18T16:56:53", 
    "_body": "", 
    "_head": "1601", 
    "_date": "35b8105210"
  }, 
  {
    "_type": "TempBasal", 
    "temp": "absolute", 
    "_description": "TempBasal 2016-02-18T16:56:53 head[2], body[1] op[0x33]", 
    "timestamp": "2016-02-18T16:56:53", 
    "_body": "00", 
    "_head": "3300", 
    "rate": 0.0, 
    "_date": "35b8105210"
  }, 
  {
    "_type": "TempBasalDuration", 
    "duration (min)": 30, 
    "_description": "TempBasalDuration 2016-02-18T16:56:52 head[2], body[0] op[0x16]", 
    "timestamp": "2016-02-18T16:56:52", 
    "_body": "", 
    "_head": "1601", 
    "_date": "34b8105210"
  }, 
  {
    "_type": "TempBasal", 
    "temp": "absolute", 
    "_description": "TempBasal 2016-02-18T16:56:52 head[2], body[1] op[0x33]", 
    "timestamp": "2016-02-18T16:56:52", 
    "_body": "00", 
    "_head": "3300", 
    "rate": 0.0, 
    "_date": "34b8105210"
  }, 
  {
    "_type": "TempBasalDuration", 
    "duration (min)": 30, 
    "_description": "TempBasalDuration 2016-02-18T16:51:58 head[2], body[0] op[0x16]", 
    "timestamp": "2016-02-18T16:51:58", 
    "_body": "", 
    "_head": "1601", 
    "_date": "3ab3105210"
  }, 
  {
    "_type": "TempBasal", 
    "temp": "absolute", 
    "_description": "TempBasal 2016-02-18T16:51:58 head[2], body[1] op[0x33]", 
    "timestamp": "2016-02-18T16:51:58", 
    "_body": "00", 
    "_head": "3300", 
    "rate": 0.0, 
    "_date": "3ab3105210"
  }, 
  {
    "_type": "TempBasalDuration", 
    "duration (min)": 30, 
    "_description": "TempBasalDuration 2016-02-18T16:51:56 head[2], body[0] op[0x16]", 
    "timestamp": "2016-02-18T16:51:56", 
    "_body": "", 
    "_head": "1601", 
    "_date": "38b3105210"
  }, 
  {
    "_type": "TempBasal", 
    "temp": "absolute", 
    "_description": "TempBasal 2016-02-18T16:51:56 head[2], body[1] op[0x33]", 
    "timestamp": "2016-02-18T16:51:56", 
    "_body": "00", 
    "_head": "3300", 
    "rate": 0.0, 
    "_date": "38b3105210"
  }, 
  {
    "_type": "TempBasalDuration", 
    "duration (min)": 30, 
    "_description": "TempBasalDuration 2016-02-18T16:51:55 head[2], body[0] op[0x16]", 
    "timestamp": "2016-02-18T16:51:55", 
    "_body": "", 
    "_head": "1601", 
    "_date": "37b3105210"
  }, 
  {
    "_type": "TempBasal", 
    "temp": "absolute", 
    "_description": "TempBasal 2016-02-18T16:51:55 head[2], body[1] op[0x33]", 
    "timestamp": "2016-02-18T16:51:55", 
    "_body": "00", 
    "_head": "3300", 
    "rate": 0.0, 
    "_date": "37b3105210"
  }, 
  {
    "_type": "TempBasalDuration", 
    "duration (min)": 0, 
    "_description": "TempBasalDuration 2016-02-18T16:13:57 head[2], body[0] op[0x16]", 
    "timestamp": "2016-02-18T16:13:57", 
    "_body": "", 
    "_head": "1600", 
    "_date": "398d105210"
  }, 
  {
    "_type": "TempBasal", 
    "temp": "absolute", 
    "_description": "TempBasal 2016-02-18T16:13:57 head[2], body[1] op[0x33]", 
    "timestamp": "2016-02-18T16:13:57", 
    "_body": "00", 
    "_head": "3300", 
    "rate": 0.0, 
    "_date": "398d105210"
  }, 
  {
    "_type": "TempBasalDuration", 
    "duration (min)": 0, 
    "_description": "TempBasalDuration 2016-02-18T16:13:54 head[2], body[0] op[0x16]", 
    "timestamp": "2016-02-18T16:13:54", 
    "_body": "", 
    "_head": "1600", 
    "_date": "368d105210"
  }, 
  {
    "_type": "TempBasal", 
    "temp": "absolute", 
    "_description": "TempBasal 2016-02-18T16:13:54 head[2], body[1] op[0x33]", 
    "timestamp": "2016-02-18T16:13:54", 
    "_body": "00", 
    "_head": "3300", 
    "rate": 0.0, 
    "_date": "368d105210"
  }, 
  {
    "_type": "TempBasalDuration", 
    "duration (min)": 0, 
    "_description": "TempBasalDuration 2016-02-18T16:13:53 head[2], body[0] op[0x16]", 
    "timestamp": "2016-02-18T16:13:53", 
    "_body": "", 
    "_head": "1600", 
    "_date": "358d105210"
  }, 
  {
    "_type": "TempBasal", 
    "temp": "absolute", 
    "_description": "TempBasal 2016-02-18T16:13:53 head[2], body[1] op[0x33]", 
    "timestamp": "2016-02-18T16:13:53", 
    "_body": "00", 
    "_head": "3300", 
    "rate": 0.0, 
    "_date": "358d105210"
  }, 
  {
    "_type": "TempBasalDuration", 
    "duration (min)": 30, 
    "_description": "TempBasalDuration 2016-02-18T16:08:55 head[2], body[0] op[0x16]", 
    "timestamp": "2016-02-18T16:08:55", 
    "_body": "", 
    "_head": "1601", 
    "_date": "3788105210"
  }, 
  {
    "_type": "TempBasal", 
    "temp": "absolute", 
    "_description": "TempBasal 2016-02-18T16:08:55 head[2], body[1] op[0x33]", 
    "timestamp": "2016-02-18T16:08:55", 
    "_body": "00", 
    "_head": "3308", 
    "rate": 0.2, 
    "_date": "3788105210"
  }, 
  {
    "_type": "TempBasalDuration", 
    "duration (min)": 30, 
    "_description": "TempBasalDuration 2016-02-18T16:08:52 head[2], body[0] op[0x16]", 
    "timestamp": "2016-02-18T16:08:52", 
    "_body": "", 
    "_head": "1601", 
    "_date": "3488105210"
  }, 
  {
    "_type": "TempBasal", 
    "temp": "absolute", 
    "_description": "TempBasal 2016-02-18T16:08:52 head[2], body[1] op[0x33]", 
    "timestamp": "2016-02-18T16:08:52", 
    "_body": "00", 
    "_head": "3308", 
    "rate": 0.2, 
    "_date": "3488105210"
  }, 
  {
    "_type": "TempBasalDuration", 
    "duration (min)": 30, 
    "_description": "TempBasalDuration 2016-02-18T16:08:51 head[2], body[0] op[0x16]", 
    "timestamp": "2016-02-18T16:08:51", 
    "_body": "", 
    "_head": "1601", 
    "_date": "3388105210"
  }, 
  {
    "_type": "TempBasal", 
    "temp": "absolute", 
    "_description": "TempBasal 2016-02-18T16:08:51 head[2], body[1] op[0x33]", 
    "timestamp": "2016-02-18T16:08:51", 
    "_body": "00", 
    "_head": "3308", 
    "rate": 0.2, 
    "_date": "3388105210"
  }, 
  {
    "_type": "TempBasalDuration", 
    "duration (min)": 0, 
    "_description": "TempBasalDuration 2016-02-18T15:30:10 head[2], body[0] op[0x16]", 
    "timestamp": "2016-02-18T15:30:10", 
    "_body": "", 
    "_head": "1600", 
    "_date": "0a9e0f5210"
  }, 
  {
    "_type": "TempBasal", 
    "temp": "absolute", 
    "_description": "TempBasal 2016-02-18T15:30:10 head[2], body[1] op[0x33]", 
    "timestamp": "2016-02-18T15:30:10", 
    "_body": "00", 
    "_head": "3300", 
    "rate": 0.0, 
    "_date": "0a9e0f5210"
  }, 
  {
    "_type": "TempBasalDuration", 
    "duration (min)": 0, 
    "_description": "TempBasalDuration 2016-02-18T15:30:08 head[2], body[0] op[0x16]", 
    "timestamp": "2016-02-18T15:30:08", 
    "_body": "", 
    "_head": "1600", 
    "_date": "089e0f5210"
  }, 
  {
    "_type": "TempBasal", 
    "temp": "absolute", 
    "_description": "TempBasal 2016-02-18T15:30:08 head[2], body[1] op[0x33]", 
    "timestamp": "2016-02-18T15:30:08", 
    "_body": "00", 
    "_head": "3300", 
    "rate": 0.0, 
    "_date": "089e0f5210"
  }, 
  {
    "_type": "TempBasalDuration", 
    "duration (min)": 0, 
    "_description": "TempBasalDuration 2016-02-18T15:30:06 head[2], body[0] op[0x16]", 
    "timestamp": "2016-02-18T15:30:06", 
    "_body": "", 
    "_head": "1600", 
    "_date": "069e0f5210"
  }, 
  {
    "_type": "TempBasal", 
    "temp": "absolute", 
    "_description": "TempBasal 2016-02-18T15:30:06 head[2], body[1] op[0x33]", 
    "timestamp": "2016-02-18T15:30:06", 
    "_body": "00", 
    "_head": "3300", 
    "rate": 0.0, 
    "_date": "069e0f5210"
  }, 
  {
    "_type": "TempBasalDuration", 
    "duration (min)": 30, 
    "_description": "TempBasalDuration 2016-02-18T15:05:04 head[2], body[0] op[0x16]", 
    "timestamp": "2016-02-18T15:05:04", 
    "_body": "", 
    "_head": "1601", 
    "_date": "04850f5210"
  }, 
  {
    "_type": "TempBasal", 
    "temp": "absolute", 
    "_description": "TempBasal 2016-02-18T15:05:04 head[2], body[1] op[0x33]", 
    "timestamp": "2016-02-18T15:05:04", 
    "_body": "00", 
    "_head": "335b", 
    "rate": 2.275, 
    "_date": "04850f5210"
  }, 
  {
    "_type": "TempBasalDuration", 
    "duration (min)": 30, 
    "_description": "TempBasalDuration 2016-02-18T15:05:01 head[2], body[0] op[0x16]", 
    "timestamp": "2016-02-18T15:05:01", 
    "_body": "", 
    "_head": "1601", 
    "_date": "01850f5210"
  }, 
  {
    "_type": "TempBasal", 
    "temp": "absolute", 
    "_description": "TempBasal 2016-02-18T15:05:01 head[2], body[1] op[0x33]", 
    "timestamp": "2016-02-18T15:05:01", 
    "_body": "00", 
    "_head": "335b", 
    "rate": 2.275, 
    "_date": "01850f5210"
  }, 
  {
    "_type": "TempBasalDuration", 
    "duration (min)": 0, 
    "_description": "TempBasalDuration 2016-02-18T15:02:01 head[2], body[0] op[0x16]", 
    "timestamp": "2016-02-18T15:02:01", 
    "_body": "", 
    "_head": "1600", 
    "_date": "01820f5210"
  }, 
  {
    "_type": "TempBasal", 
    "temp": "absolute", 
    "_description": "TempBasal 2016-02-18T15:02:01 head[2], body[1] op[0x33]", 
    "timestamp": "2016-02-18T15:02:01", 
    "_body": "00", 
    "_head": "3300", 
    "rate": 0.0, 
    "_date": "01820f5210"
  }, 
  {
    "_type": "TempBasalDuration", 
    "duration (min)": 0, 
    "_description": "TempBasalDuration 2016-02-18T15:01:57 head[2], body[0] op[0x16]", 
    "timestamp": "2016-02-18T15:01:57", 
    "_body": "", 
    "_head": "1600", 
    "_date": "39810f5210"
  }, 
  {
    "_type": "TempBasal", 
    "temp": "absolute", 
    "_description": "TempBasal 2016-02-18T15:01:57 head[2], body[1] op[0x33]", 
    "timestamp": "2016-02-18T15:01:57", 
    "_body": "00", 
    "_head": "3300", 
    "rate": 0.0, 
    "_date": "39810f5210"
  }, 
  {
    "_type": "TempBasalDuration", 
    "duration (min)": 30, 
    "_description": "TempBasalDuration 2016-02-18T14:42:12 head[2], body[0] op[0x16]", 
    "timestamp": "2016-02-18T14:42:12", 
    "_body": "", 
    "_head": "1601", 
    "_date": "0caa0e5210"
  }, 
  {
    "_type": "TempBasal", 
    "temp": "absolute", 
    "_description": "TempBasal 2016-02-18T14:42:12 head[2], body[1] op[0x33]", 
    "timestamp": "2016-02-18T14:42:12", 
    "_body": "00", 
    "_head": "3300", 
    "rate": 0.0, 
    "_date": "0caa0e5210"
  }, 
  {
    "_type": "TempBasalDuration", 
    "duration (min)": 30, 
    "_description": "TempBasalDuration 2016-02-18T14:42:08 head[2], body[0] op[0x16]", 
    "timestamp": "2016-02-18T14:42:08", 
    "_body": "", 
    "_head": "1601", 
    "_date": "08aa0e5210"
  }, 
  {
    "_type": "TempBasal", 
    "temp": "absolute", 
    "_description": "TempBasal 2016-02-18T14:42:08 head[2], body[1] op[0x33]", 
    "timestamp": "2016-02-18T14:42:08", 
    "_body": "00", 
    "_head": "3300", 
    "rate": 0.0, 
    "_date": "08aa0e5210"
  }, 
  {
    "_type": "TempBasalDuration", 
    "duration (min)": 0, 
    "_description": "TempBasalDuration 2016-02-18T14:19:54 head[2], body[0] op[0x16]", 
    "timestamp": "2016-02-18T14:19:54", 
    "_body": "", 
    "_head": "1600", 
    "_date": "36930e5210"
  }, 
  {
    "_type": "TempBasal", 
    "temp": "absolute", 
    "_description": "TempBasal 2016-02-18T14:19:54 head[2], body[1] op[0x33]", 
    "timestamp": "2016-02-18T14:19:54", 
    "_body": "00", 
    "_head": "3300", 
    "rate": 0.0, 
    "_date": "36930e5210"
  }, 
  {
    "_type": "TempBasalDuration", 
    "duration (min)": 0, 
    "_description": "TempBasalDuration 2016-02-18T14:19:51 head[2], body[0] op[0x16]", 
    "timestamp": "2016-02-18T14:19:51", 
    "_body": "", 
    "_head": "1600", 
    "_date": "33930e5210"
  }, 
  {
    "_type": "TempBasal", 
    "temp": "absolute", 
    "_description": "TempBasal 2016-02-18T14:19:51 head[2], body[1] op[0x33]", 
    "timestamp": "2016-02-18T14:19:51", 
    "_body": "00", 
    "_head": "3300", 
    "rate": 0.0, 
    "_date": "33930e5210"
  }, 
  {
    "_type": "TempBasalDuration", 
    "duration (min)": 0, 
    "_description": "TempBasalDuration 2016-02-18T14:19:50 head[2], body[0] op[0x16]", 
    "timestamp": "2016-02-18T14:19:50", 
    "_body": "", 
    "_head": "1600", 
    "_date": "32930e5210"
  }, 
  {
    "_type": "TempBasal", 
    "temp": "absolute", 
    "_description": "TempBasal 2016-02-18T14:19:50 head[2], body[1] op[0x33]", 
    "timestamp": "2016-02-18T14:19:50", 
    "_body": "00", 
    "_head": "3300", 
    "rate": 0.0, 
    "_date": "32930e5210"
  }, 
  {
    "_type": "TempBasalDuration", 
    "duration (min)": 30, 
    "_description": "TempBasalDuration 2016-02-18T14:14:08 head[2], body[0] op[0x16]", 
    "timestamp": "2016-02-18T14:14:08", 
    "_body": "", 
    "_head": "1601", 
    "_date": "088e0e5210"
  }, 
  {
    "_type": "TempBasal", 
    "temp": "absolute", 
    "_description": "TempBasal 2016-02-18T14:14:08 head[2], body[1] op[0x33]", 
    "timestamp": "2016-02-18T14:14:08", 
    "_body": "00", 
    "_head": "3300", 
    "rate": 0.0, 
    "_date": "088e0e5210"
  }, 
  {
    "_type": "TempBasalDuration", 
    "duration (min)": 30, 
    "_description": "TempBasalDuration 2016-02-18T14:14:05 head[2], body[0] op[0x16]", 
    "timestamp": "2016-02-18T14:14:05", 
    "_body": "", 
    "_head": "1601", 
    "_date": "058e0e5210"
  }, 
  {
    "_type": "TempBasal", 
    "temp": "absolute", 
    "_description": "TempBasal 2016-02-18T14:14:05 head[2], body[1] op[0x33]", 
    "timestamp": "2016-02-18T14:14:05", 
    "_body": "00", 
    "_head": "3300", 
    "rate": 0.0, 
    "_date": "058e0e5210"
  }, 
  {
    "_type": "TempBasalDuration", 
    "duration (min)": 30, 
    "_description": "TempBasalDuration 2016-02-18T14:14:04 head[2], body[0] op[0x16]", 
    "timestamp": "2016-02-18T14:14:04", 
    "_body": "", 
    "_head": "1601", 
    "_date": "048e0e5210"
  }, 
  {
    "_type": "TempBasal", 
    "temp": "absolute", 
    "_description": "TempBasal 2016-02-18T14:14:04 head[2], body[1] op[0x33]", 
    "timestamp": "2016-02-18T14:14:04", 
    "_body": "00", 
    "_head": "3300", 
    "rate": 0.0, 
    "_date": "048e0e5210"
  }, 
  {
    "_type": "TempBasalDuration", 
    "duration (min)": 30, 
    "_description": "TempBasalDuration 2016-02-18T14:04:57 head[2], body[0] op[0x16]", 
    "timestamp": "2016-02-18T14:04:57", 
    "_body": "", 
    "_head": "1601", 
    "_date": "39840e5210"
  }, 
  {
    "_type": "TempBasal", 
    "temp": "absolute", 
    "_description": "TempBasal 2016-02-18T14:04:57 head[2], body[1] op[0x33]", 
    "timestamp": "2016-02-18T14:04:57", 
    "_body": "00", 
    "_head": "3308", 
    "rate": 0.2, 
    "_date": "39840e5210"
  }, 
  {
    "_type": "TempBasalDuration", 
    "duration (min)": 30, 
    "_description": "TempBasalDuration 2016-02-18T14:04:55 head[2], body[0] op[0x16]", 
    "timestamp": "2016-02-18T14:04:55", 
    "_body": "", 
    "_head": "1601", 
    "_date": "37840e5210"
  }, 
  {
    "_type": "TempBasal", 
    "temp": "absolute", 
    "_description": "TempBasal 2016-02-18T14:04:55 head[2], body[1] op[0x33]", 
    "timestamp": "2016-02-18T14:04:55", 
    "_body": "00", 
    "_head": "3308", 
    "rate": 0.2, 
    "_date": "37840e5210"
  }, 
  {
    "_type": "TempBasalDuration", 
    "duration (min)": 30, 
    "_description": "TempBasalDuration 2016-02-18T14:04:53 head[2], body[0] op[0x16]", 
    "timestamp": "2016-02-18T14:04:53", 
    "_body": "", 
    "_head": "1601", 
    "_date": "35840e5210"
  }, 
  {
    "_type": "TempBasal", 
    "temp": "absolute", 
    "_description": "TempBasal 2016-02-18T14:04:53 head[2], body[1] op[0x33]", 
    "timestamp": "2016-02-18T14:04:53", 
    "_body": "00", 
    "_head": "3308", 
    "rate": 0.2, 
    "_date": "35840e5210"
  }
]