{
  "device": "openaps://mursefree", 
  "pump": {
    "battery": {
      "status": "normal", 
      "voltage": 1.43
    }, 
    "status": {
      "status": "normal", 
      "timestamp": "2016-02-17T00:51:33.000Z", 
      "bolusing": false, 
      "suspended": false
    }, 
    "reservoir": 61, 
    "clock": "2016-02-16T16:49:44-08:00"
  }, 
  "openaps": {
    "suggested": {
      "bg": 127, 
      "temp": "absolute", 
      "snoozeBG": 107, 
      "timestamp": "2016-02-17T00:51:55.000Z", 
      "reason": "Eventual BG 74<90, bolus snooze: eventual BG range 74-107", 
      "eventualBG": 74, 
      "mealAssist": "Off: Carbs: 42 Boluses: 4.5 Target: 97.5 Deviation: 8 BGI: -2.75", 
      "tick": -1
    }, 
    "iob": {
      "netbasalinsulin": 1, 
      "timestamp": "2016-02-17T00:51:54.000Z", 
      "basaliob": 0.928, 
      "activity": 0.022, 
      "bolussnooze": 0.882, 
      "iob": 2.425
    }, 
    "enacted": {
      "requested": {
        "duration": 30, 
        "rate": 4.4, 
        "temp": "absolute"
      }, 
      "bg": 116, 
      "temp": "absolute", 
      "snoozeBG": 126, 
      "timestamp": "2016-02-16T23:28:25.000Z", 
      "reason": "Eventual BG 143>=105, temp 3.2<4.38U/hr", 
      "rate": 4.4, 
      "eventualBG": 143, 
      "recieved": true, 
      "duration": 30, 
      "mealAssist": "On: Carbs: 26 Boluses: 2.8 Target: 92.5 Deviation: 17 BGI: -2.3", 
      "tick": "+5"
    }
  }
}